orbis_plugin_metrics_binary_classification_metrics/__init__.py
orbis_plugin_metrics_binary_classification_metrics/main.py
tests/__init__.py
tests/confusion_matrices.py
tests/test_main.py
orbis_plugin_metrics_binary_classification_metrics-2.2.4.dist-info/LICENSE
orbis_plugin_metrics_binary_classification_metrics-2.2.4.dist-info/METADATA
orbis_plugin_metrics_binary_classification_metrics-2.2.4.dist-info/WHEEL
orbis_plugin_metrics_binary_classification_metrics-2.2.4.dist-info/top_level.txt
orbis_plugin_metrics_binary_classification_metrics-2.2.4.dist-info/RECORD
